{
  "app": {
    "[project]/src/app/_not-found/page": [
      "static/media/83afe278b6a6bb3c-s.p.3a6ba036.woff2"
    ],
    "[project]/src/app/caja/page": [
      "static/media/83afe278b6a6bb3c-s.p.3a6ba036.woff2"
    ],
    "[project]/src/app/finanzas/page": [
      "static/media/83afe278b6a6bb3c-s.p.3a6ba036.woff2"
    ],
    "[project]/src/app/login/page": [
      "static/media/83afe278b6a6bb3c-s.p.3a6ba036.woff2"
    ],
    "[project]/src/app/logistica/page": [
      "static/media/83afe278b6a6bb3c-s.p.3a6ba036.woff2"
    ],
    "[project]/src/app/page": [
      "static/media/83afe278b6a6bb3c-s.p.3a6ba036.woff2"
    ],
    "[project]/src/app/proveedores/page": [
      "static/media/83afe278b6a6bb3c-s.p.3a6ba036.woff2"
    ],
    "[project]/src/app/rrhh/page": [
      "static/media/83afe278b6a6bb3c-s.p.3a6ba036.woff2"
    ],
    "[project]/src/app/settings/auditoria/page": [
      "static/media/83afe278b6a6bb3c-s.p.3a6ba036.woff2"
    ],
    "[project]/src/app/settings/page": [
      "static/media/83afe278b6a6bb3c-s.p.3a6ba036.woff2"
    ],
    "[project]/src/app/web/page": [
      "static/media/83afe278b6a6bb3c-s.p.3a6ba036.woff2"
    ]
  },
  "appUsingSizeAdjust": true,
  "pages": {},
  "pagesUsingSizeAdjust": false
}